Workbook

Sheet Summary
A1: Retail Sales Data Analysis
A2: Prepared by Shreya Nag
A4: About this project
A5: This project analyzes a retail sales dataset of 2024 orders to find which products and regions perform best and how sales change through the year. The goal was to turn raw transaction data into clear business insights.
A7: What I did
A8: 1. Collected a transactional sales dataset (orders, customers, regions, categories, sales and profit).
A9: 2. Cleaned and prepared the data: checked for duplicate orders, blank values, and made sure dates, sales and profit were in the correct numeric/date formats.
A10: 3. Built summary tables using SUMIF and AVERAGEIF formulas to total sales and profit by category, by region, and by month.
A11: 4. Created charts (bar and line) to visualize the findings, the way a simple dashboard would.
A12: 5. Wrote up the key findings below.
A14: Key findings
A15: - Furniture generated the highest total sales, while Office Supplies had the strongest profit margin because it carries smaller discounts.
... A26: - 'Summary' tab (this page): the project overview and findings.

Sheet Sales Data
A1: Order ID | B1: Order Date | C1: Customer | D1: Segment | E1: Region | F1: Category | G1: Product | H1: Quantity | I1: Discount | J1: Sales | K1: Profit | L1: Month
A2: ORD-1066 | B2: 45293 | C2: Arjun Reddy | D2: Corporate | E2: East | F2: Furniture | G2: Bookcase | H2: 8 | I2: 0.25 | J2: 36000 | K2: 720 | L2: =TEXT(B2,"yyyy-mm") -> 2024-01
A3: ORD-1096 | B3: 45295 | C3: Myra Reddy | D3: Consumer | E3: South | F3: Technology | G3: Smartphone | H3: 7 | I3: 0 | J3: 196000 | K3: 35280 | L3: =TEXT(B3,"yyyy-mm") -> 2024-01
A4: ORD-1133 | B4: 45305 | C4: Myra Verma | D4: Consumer | E4: East | F4: Office Supplies | G4: Pens (Pack) | H4: 8 | I4: 0.15 | J4: 1020 | K4: 183.6 | L4: =TEXT(B4,"yyyy-mm") -> 2024-01
A5: ORD-1070 | B5: 45306 | C5: Sara Verma | D5: Consumer | E5: South | F5: Technology | G5: Headphones | H5: 1 | I5: 0.05 | J5: 3325 | K5: 465.5 | L5: =TEXT(B5,"yyyy-mm") -> 2024-01
A6: ORD-1120 | B6: 45306 | C6: Aditya Patel | D6: Corporate | E6: West | F6: Furniture | G6: Office Chair | H6: 6 | I6: 0.25 | J6: 36000 | K6: 720 | L6: =TEXT(B6,"yyyy-mm") -> 2024-01
A7: ORD-1142 | B7: 45306 | C7: Dev Patel | D7: Corporate | E7: North | F7: Technology | G7: Laptop | H7: 5 | I7: 0.2 | J7: 220000 | K7: 4400 | L7: =TEXT(B7,"yyyy-mm") -> 2024-01
A8: ORD-1042 | B8: 45307 | C8: Navya Iyer | D8: Corporate | E8: North | F8: Technology | G8: Smartphone | H8: 1 | I8: 0.15 | J8: 23800 | K8: 1428 | L8: =TEXT(B8,"yyyy-mm") -> 2024-01
A9: ORD-1021 | B9: 45312 | C9: Myra Verma | D9: Corporate | E9: South | F9: Furniture | G9: Desk | H9: 4 | I9: 0.2 | J9: 48000 | K9: 2880 | L9: =TEXT(B9,"yyyy-mm") -> 2024-01
A10: ORD-1100 | B10: 45315 | C10: Myra Sharma | D10: Consumer | E10: East | F10: Technology | G10: Monitor | H10: 1 | I10: 0 | J10: 12000 | K10: 2160 | L10: =TEXT(B10,"yyyy-mm") -> 2024-01
A11: ORD-1159 | B11: 45317 | C11: Aarav Verma | D11: Corporate | E11: East | F11: Office Supplies | G11: Binder | H11: 4 | I11: 0.2 | J11: 640 | K11: 89.6 | L11: =TEXT(B11,"yyyy-mm") -> 2024-01
A12: ORD-1093 | B12: 45318 | C12: Riya Das | D12: Consumer | E12: South | F12: Furniture | G12: Sofa | H12: 5 | I12: 0.05 | J12: 152000 | K12: 27360 | L12: =TEXT(B12,"yyyy-mm") -> 2024-01
A13: ORD-1098 | B13: 45318 | C13: Diya Reddy | D13: Home Office | E13: West | F13: Technology | G13: Smartphone | H13: 1 | I13: 0.2 | J13: 22400 | K13: 448 | L13: =TEXT(B13,"yyyy-mm") -> 2024-01
... A169: ORD-1118 | B169: 45656 | C169: Anika Verma | D169: Corporate | E169: South | F169: Office Supplies | G169: Printer Paper | H169: 5 | I169: 0 | J169: 1750 | K169: 525 | L169: =TEXT(B169,"yyyy-mm") -> 2024-12

Sheet Analysis
A1: Sales Analysis Summary
A2: Built from the Sales Data sheet using SUMIF / AVERAGEIF formulas. Change the data and these update automatically.
A4: Sales & Profit by Category
A5: Category | B5: Total Sales | C5: Total Profit | D5: Profit Margin
A6: Technology | B6: =SUMIF('Sales Data'!$F$2:$F$169,A6,'Sales Data'!$J$2:$J$169) -> 3427775 | C6: =SUMIF('Sales Data'!$F$2:$F$169,A6,'Sales Data'!$K$2:$K$169) -> 266322.5 | D6: =IF(B6=0,0,C6/B6) -> 0.077695444
A7: Furniture | B7: =SUMIF('Sales Data'!$F$2:$F$169,A7,'Sales Data'!$J$2:$J$169) -> 3981990 | C7: =SUMIF('Sales Data'!$F$2:$F$169,A7,'Sales Data'!$K$2:$K$169) -> 523483.8 | D7: =IF(B7=0,0,C7/B7) -> 0.13146286
A8: Office Supplies | B8: =SUMIF('Sales Data'!$F$2:$F$169,A8,'Sales Data'!$J$2:$J$169) -> 51517.5 | C8: =SUMIF('Sales Data'!$F$2:$F$169,A8,'Sales Data'!$K$2:$K$169) -> 11530.91 | D8: =IF(B8=0,0,C8/B8) -> 0.22382511
A9: Total | B9: =SUM(B6:B8) -> 7461282.5 | C9: =SUM(C6:C8) -> 801337.21 | D9: =IF(B9=0,0,C9/B9) -> 0.10739939
A12: Sales & Profit by Region
A13: Category | B13: Total Sales | C13: Total Profit | D13: Profit Margin
A14: North | B14: =SUMIF('Sales Data'!$E$2:$E$169,A14,'Sales Data'!$J$2:$J$169) -> 1183155 | C14: =SUMIF('Sales Data'!$E$2:$E$169,A14,'Sales Data'!$K$2:$K$169) -> 82987.3 | D14: =IF(B14=0,0,C14/B14) -> 0.070140683
A15: South | B15: =SUMIF('Sales Data'!$E$2:$E$169,A15,'Sales Data'!$J$2:$J$169) -> 1702477.5 | C15: =SUMIF('Sales Data'!$E$2:$E$169,A15,'Sales Data'!$K$2:$K$169) -> 161413.15 | D15: =IF(B15=0,0,C15/B15) -> 0.094810739
A16: East | B16: =SUMIF('Sales Data'!$E$2:$E$169,A16,'Sales Data'!$J$2:$J$169) -> 2800150.5 | C16: =SUMIF('Sales Data'!$E$2:$E$169,A16,'Sales Data'!$K$2:$K$169) -> 363976.33 | D16: =IF(B16=0,0,C16/B16) -> 0.12998456
A17: West | B17: =SUMIF('Sales Data'!$E$2:$E$169,A17,'Sales Data'!$J$2:$J$169) -> 1775499.5 | C17: =SUMIF('Sales Data'!$E$2:$E$169,A17,'Sales Data'!$K$2:$K$169) -> 192960.43 | D17: =IF(B17=0,0,C17/B17) -> 0.10867952
A18: Total | B18: =SUM(B14:B17) -> 7461282.5 | C18: =SUM(C14:C17) -> 801337.21 | D18: =IF(B18=0,0,C18/B18) -> 0.10739939
A21: Monthly Sales Trend
A22: Month | B22: Total Sales
A23: 2024-01 | B23: =SUMIF('Sales Data'!$L$2:$L$169,A23,'Sales Data'!$J$2:$J$169) -> 761985
A24: 2024-02 | B24: =SUMIF('Sales Data'!$L$2:$L$169,A24,'Sales Data'!$J$2:$J$169) -> 263972.5
A25: 2024-03 | B25: =SUMIF('Sales Data'!$L$2:$L$169,A25,'Sales Data'!$J$2:$J$169) -> 497267.5
A26: 2024-04 | B26: =SUMIF('Sales Data'!$L$2:$L$169,A26,'Sales Data'!$J$2:$J$169) -> 372525
A27: 2024-05 | B27: =SUMIF('Sales Data'!$L$2:$L$169,A27,'Sales Data'!$J$2:$J$169) -> 1195053
A28: 2024-06 | B28: =SUMIF('Sales Data'!$L$2:$L$169,A28,'Sales Data'!$J$2:$J$169) -> 85342
A29: 2024-07 | B29: =SUMIF('Sales Data'!$L$2:$L$169,A29,'Sales Data'!$J$2:$J$169) -> 486750
A30: 2024-08 | B30: =SUMIF('Sales Data'!$L$2:$L$169,A30,'Sales Data'!$J$2:$J$169) -> 448002.5
A31: 2024-09 | B31: =SUMIF('Sales Data'!$L$2:$L$169,A31,'Sales Data'!$J$2:$J$169) -> 637380
A32: 2024-10 | B32: =SUMIF('Sales Data'!$L$2:$L$169,A32,'Sales Data'!$J$2:$J$169) -> 677927.5
A33: 2024-11 | B33: =SUMIF('Sales Data'!$L$2:$L$169,A33,'Sales Data'!$J$2:$J$169) -> 1181317.5
A34: 2024-12 | B34: =SUMIF('Sales Data'!$L$2:$L$169,A34,'Sales Data'!$J$2:$J$169) -> 853760
